aws_ssabuilders/aws_bootstrap_kit/__init__.py
aws_ssabuilders/aws_bootstrap_kit/py.typed
aws_ssabuilders/aws_bootstrap_kit/_jsii/__init__.py
aws_ssabuilders/aws_bootstrap_kit/_jsii/aws-bootstrap-kit@0.7.8.jsii.tgz
aws_ssabuilders.aws_bootstrap_kit-0.7.8.dist-info/LICENSE
aws_ssabuilders.aws_bootstrap_kit-0.7.8.dist-info/METADATA
aws_ssabuilders.aws_bootstrap_kit-0.7.8.dist-info/NOTICE
aws_ssabuilders.aws_bootstrap_kit-0.7.8.dist-info/WHEEL
aws_ssabuilders.aws_bootstrap_kit-0.7.8.dist-info/top_level.txt
aws_ssabuilders.aws_bootstrap_kit-0.7.8.dist-info/RECORD
