Metadata-Version: 2.1
Name: aws-ssabuilders.aws-bootstrap-kit
Version: 0.7.8
Summary: aws-bootstrap-kit
Home-page: https://github.com/awslabs/aws-bootstrap-kit
Author: AWS EMEA SA Specialist Builders<chazalf@amazon.com>
License: Apache-2.0
Project-URL: Source, https://github.com/awslabs/aws-bootstrap-kit
Platform: UNKNOWN
Classifier: Intended Audience :: Developers
Classifier: Operating System :: OS Independent
Classifier: Programming Language :: JavaScript
Classifier: Programming Language :: Python :: 3 :: Only
Classifier: Programming Language :: Python :: 3.7
Classifier: Programming Language :: Python :: 3.8
Classifier: Programming Language :: Python :: 3.9
Classifier: Programming Language :: Python :: 3.10
Classifier: Typing :: Typed
Classifier: Development Status :: 5 - Production/Stable
Classifier: License :: OSI Approved
Requires-Python: ~=3.7
License-File: LICENSE
License-File: NOTICE
Requires-Dist: aws-cdk-lib (<3.0.0,>=2.60.0)
Requires-Dist: constructs (<11.0.0,>=10.0.5)
Requires-Dist: jsii (<2.0.0,>=1.73.0)
Requires-Dist: publication (>=0.0.3)
Requires-Dist: typeguard (~=2.13.3)
